menusbar/__init__.py
menusbar/core/Dialog.py
menusbar/core/FileUtils.py
menusbar/core/MenusBar.py
menusbar/core/__init__.py
EasyMenusBar-0.3.5.dist-info/LICENSE
EasyMenusBar-0.3.5.dist-info/METADATA
EasyMenusBar-0.3.5.dist-info/WHEEL
EasyMenusBar-0.3.5.dist-info/top_level.txt
EasyMenusBar-0.3.5.dist-info/RECORD
